azureml/__init__.py
azureml/designer/__init__.py
azureml/designer/serving/__init__.py
azureml/designer/serving/package_info.py
azureml/designer/serving/dagengine/__init__.py
azureml/designer/serving/dagengine/constants.py
azureml/designer/serving/dagengine/converter.py
azureml/designer/serving/dagengine/dag.py
azureml/designer/serving/dagengine/dag_node.py
azureml/designer/serving/dagengine/graph_spec.py
azureml/designer/serving/dagengine/mock_ds_invoker.py
azureml/designer/serving/dagengine/mock_request.py
azureml/designer/serving/dagengine/module_host.py
azureml/designer/serving/dagengine/processor.py
azureml/designer/serving/dagengine/request_handler.py
azureml/designer/serving/dagengine/score_exceptions.py
azureml/designer/serving/dagengine/score_implementation.py
azureml/designer/serving/dagengine/static_source.py
azureml/designer/serving/dagengine/utils.py
azureml_designer_serving-0.0.15.dist-info/METADATA
azureml_designer_serving-0.0.15.dist-info/WHEEL
azureml_designer_serving-0.0.15.dist-info/top_level.txt
azureml_designer_serving-0.0.15.dist-info/RECORD
