Metadata-Version: 2.1
Name: azureml-designer-serving
Version: 0.0.15
Summary: Provide functionalities to invoke Azure Machine Learning designer built-in modules in deployment service.
Author: Microsoft Crop
Platform: any
Classifier: Programming Language :: Python :: 3
Classifier: License :: Other/Proprietary License
Classifier: Operating System :: OS Independent
Requires-Python: >=3.8
Requires-Dist: azureml-defaults (==1.54.0)
Requires-Dist: azureml-designer-core[image,model] (>=0.0.80)
Requires-Dist: azureml-contrib-services
